database_connector/__init__.py
database_connector/database_connector.py
database_connector-2.2.3.dist-info/AUTHORS.rst
database_connector-2.2.3.dist-info/METADATA
database_connector-2.2.3.dist-info/WHEEL
database_connector-2.2.3.dist-info/entry_points.txt
database_connector-2.2.3.dist-info/top_level.txt
database_connector-2.2.3.dist-info/RECORD
